agentsociety_benchmark/__init__.py
agentsociety_benchmark/runner.py
agentsociety_benchmark/benchmarks/__init__.py
agentsociety_benchmark/benchmarks/BehaviorModeling/README.md
agentsociety_benchmark/benchmarks/BehaviorModeling/README_zh.md
agentsociety_benchmark/benchmarks/BehaviorModeling/__init__.py
agentsociety_benchmark/benchmarks/BehaviorModeling/entry.py
agentsociety_benchmark/benchmarks/BehaviorModeling/evaluation.py
agentsociety_benchmark/benchmarks/BehaviorModeling/interactiontool.py
agentsociety_benchmark/benchmarks/BehaviorModeling/prepare_config.py
agentsociety_benchmark/benchmarks/BehaviorModeling/task.py
agentsociety_benchmark/benchmarks/BehaviorModeling/template_agent.py
agentsociety_benchmark/benchmarks/DailyMobility/README.md
agentsociety_benchmark/benchmarks/DailyMobility/README_zh.md
agentsociety_benchmark/benchmarks/DailyMobility/__init__.py
agentsociety_benchmark/benchmarks/DailyMobility/entry.py
agentsociety_benchmark/benchmarks/DailyMobility/evaluation.py
agentsociety_benchmark/benchmarks/DailyMobility/prepare_config.py
agentsociety_benchmark/benchmarks/DailyMobility/template_agent.py
agentsociety_benchmark/benchmarks/HurricaneMobility/README.md
agentsociety_benchmark/benchmarks/HurricaneMobility/README_zh.md
agentsociety_benchmark/benchmarks/HurricaneMobility/__init__.py
agentsociety_benchmark/benchmarks/HurricaneMobility/entry.py
agentsociety_benchmark/benchmarks/HurricaneMobility/evaluation.py
agentsociety_benchmark/benchmarks/HurricaneMobility/prepare_config.py
agentsociety_benchmark/benchmarks/HurricaneMobility/template_agent.py
agentsociety_benchmark/cli/__init__.py
agentsociety_benchmark/cli/config.py
agentsociety_benchmark/cli/main.py
agentsociety_benchmark/cli/commands/__init__.py
agentsociety_benchmark/cli/commands/clone.py
agentsociety_benchmark/cli/commands/evaluate.py
agentsociety_benchmark/cli/commands/run.py
agentsociety_benchmark/storage/__init__.py
agentsociety_benchmark/storage/_base.py
agentsociety_benchmark-0.1.4.dist-info/METADATA
agentsociety_benchmark-0.1.4.dist-info/WHEEL
agentsociety_benchmark-0.1.4.dist-info/entry_points.txt
agentsociety_benchmark-0.1.4.dist-info/licenses/LICENSE
agentsociety_benchmark-0.1.4.dist-info/RECORD
