Metadata-Version: 2.4
Name: agentsociety-benchmark
Version: 0.1.4
Summary: A tool for benchmark your agent design in different scenarios.
Author-email: Yuwei Yan <yyan791@connect.hkust-gz.edu.cn>
License:                                  Apache License
License-File: LICENSE
Classifier: Operating System :: MacOS :: MacOS X
Classifier: Operating System :: POSIX :: Linux
Classifier: Programming Language :: Python :: 3
Requires-Python: >=3.11
Requires-Dist: agentsociety>=1.5.0rc3
Requires-Dist: click>=8.0.0
Requires-Dist: datasets>=2.18.0
Requires-Dist: gitpython>=3.1.0
Requires-Dist: huggingface-hub>=0.20.0
Requires-Dist: pathlib2>=2.3.0
Requires-Dist: pyyaml>=6.0
Requires-Dist: requests>=2.25.0
Requires-Dist: tqdm>=4.64.0
